hxml.py
hxml-0.0.4.data/scripts/hxml.py
hxml-0.0.4.dist-info/METADATA
hxml-0.0.4.dist-info/WHEEL
hxml-0.0.4.dist-info/top_level.txt
hxml-0.0.4.dist-info/RECORD
