Metadata-Version: 2.1
Name: hxml
Version: 0.0.4
Home-page: https://github.com/DevHollo/hxml
Author: Hollo
Author-email: hollo1234567890e@gmail.com
Requires-Dist: hollos-get-data-recursive ==0.0.1
Requires-Dist: requests ==2.31.0
